[
    {
        "orderID": "0000000001",
        "itemID": "cf81e7d5-e17e-42da-a25d-b836f5567048",
        "itemQuantity": 2
    },
    {
        "orderID": "0000000001",
        "itemID": "6df61e06-2f5e-4bef-bf54-fb0a347eb504",
        "itemQuantity": 1
    },
    {
        "orderID": "0000000002",
        "itemID": "32c40d6c-43a4-4b22-95b3-49f228a291aa",
        "itemQuantity": 1
    },
    {
        "orderID": "0000000002",
        "itemID": "30f65103-7e55-4157-be0e-5bb65eaf6f3c",
        "itemQuantity": 1
    },
    {
        "orderID": "0000000002",
        "itemID": "2c556a37-0baf-472a-8148-2bf690d1f0b8",
        "itemQuantity": 5
    },
    {
        "orderID": "0000000003",
        "itemID": "cf81e7d5-e17e-42da-a25d-b836f5567048",
        "itemQuantity": 1
    },
    {
        "orderID": "0000000003",
        "itemID": "615d4e9a-bf46-4bc9-b06d-946d25263ac5",
        "itemQuantity": 1
    },
    {
        "orderID": "0000000004",
        "itemID": "731f2e8b-3ee5-48b2-bac4-72c9c04937c9",
        "itemQuantity": 2
    },
    {
        "orderID": "0000000005",
        "itemID": "9a79afec-b6b5-4174-a3a9-90a4b10d32c0",
        "itemQuantity": 2
    },
    {
        "orderID": "0000000006",
        "itemID": "75145460-a066-4583-9c67-040896044bdf",
        "itemQuantity": 1
    },
    {
        "orderID": "0000000007",
        "itemID": "615d4e9a-bf46-4bc9-b06d-946d25263ac5",
        "itemQuantity": 1
    },
    {
        "orderID": "0000000007",
        "itemID": "4e80cdea-ad04-4bcf-acbe-684e299afe18",
        "itemQuantity": 1
    },
    {
        "orderID": "0000000007",
        "itemID": "9a79afec-b6b5-4174-a3a9-90a4b10d32c0",
        "itemQuantity": 1
    },
    {
        "orderID": "0000000008",
        "itemID": "de741d93-749a-4ffd-924e-3ca38391c2a4",
        "itemQuantity": 1
    }
]